{
    "name": "Sprachpaket italienisch",
    "archiveName": "fishnetservices/italian-language-package",
    "sourceDir": "new_files",
    "version": "auto",
    "productNumber": "49002",
    "shortDescription": "Sprachpaket italienisch (49002)",
    "description": "Italienisches Sprachpaket ab Modified 2.0.5.0",
    "price": "free",
    "developer": "fishnetservices",
    "developerWebsite": "https://www.shopbetreuung.com/",
    "website": "https://www.shopbetreuung.com/",
    "category": "language",

    "modifiedCompatibility": [
        "2.0.5.0", "2.0.5.1"
    ]

}